filestag/__init__.py
filestag/_env.py
filestag/_iter.py
filestag/_lock.py
filestag/_version.py
filestag/azure/__init__.py
filestag/azure/async_sink.py
filestag/azure/async_source.py
filestag/azure/blob_path.py
filestag/azure/sink.py
filestag/azure/source.py
filestag/cache/__init__.py
filestag/cache/_bundle.py
filestag/cache/cache.py
filestag/cache/cache_ref.py
filestag/cache/disk_cache.py
filestag/file_path.py
filestag/file_sink.py
filestag/file_source.py
filestag/file_source_iterator.py
filestag/file_stag.py
filestag/memory_zip.py
filestag/protocols.py
filestag/shared_archive.py
filestag/sinks/__init__.py
filestag/sinks/archive.py
filestag/sinks/disk.py
filestag/sinks/zip.py
filestag/sources/__init__.py
filestag/sources/disk.py
filestag/sources/zip.py
filestag/web/__init__.py
filestag/web/fetch.py
filestag/web/web_cache.py
filestag-0.1.0.dist-info/LICENSE
filestag-0.1.0.dist-info/METADATA
filestag-0.1.0.dist-info/WHEEL
filestag-0.1.0.dist-info/RECORD
