Metadata-Version: 2.3
Name: filestag
Version: 0.1.0
Summary: A fast and efficient file access library for local and cloud storage
License: MIT
Keywords: file,storage,azure,blob,cloud,zip,archive,cache,async,io
Author: Michael Ikemann
Author-email: michael.ikemann@gmail.com
Requires-Python: >=3.12
Classifier: Development Status :: 4 - Beta
Classifier: Intended Audience :: Developers
Classifier: License :: OSI Approved :: MIT License
Classifier: Operating System :: OS Independent
Classifier: Programming Language :: Python :: 3
Classifier: Programming Language :: Python :: 3.12
Classifier: Programming Language :: Python :: 3.13
Classifier: Programming Language :: Python :: 3.14
Classifier: Topic :: System :: Filesystems
Classifier: Topic :: Software Development :: Libraries :: Python Modules
Classifier: Typing :: Typed
Provides-Extra: all
Provides-Extra: azure
Provides-Extra: dev
Requires-Dist: aiofiles (>=23.0)
Requires-Dist: aiohttp (>=3.8) ; extra == "all"
Requires-Dist: aiohttp (>=3.8) ; extra == "azure"
Requires-Dist: azure-storage-blob (>=12.0) ; extra == "all"
Requires-Dist: azure-storage-blob (>=12.0) ; extra == "azure"
Requires-Dist: httpx (>=0.24)
Requires-Dist: mypy (>=1.0) ; extra == "dev"
Requires-Dist: pydantic (>=2.0)
Requires-Dist: pytest (>=7.4) ; extra == "dev"
Requires-Dist: pytest-asyncio (>=0.21) ; extra == "dev"
Requires-Dist: pytest-cov (>=4.0) ; extra == "dev"
Requires-Dist: python-dotenv (>=1.0) ; extra == "dev"
Requires-Dist: requests (>=2.28)
Requires-Dist: ruff (>=0.1) ; extra == "dev"
Project-URL: Documentation, https://github.com/scistag/filestag#readme
Project-URL: Homepage, https://github.com/scistag/filestag
Project-URL: Issues, https://github.com/scistag/filestag/issues
Project-URL: Repository, https://github.com/scistag/filestag
